exopie/__init__.py
exopie/planet.py
exopie/property.py
exopie/tools.py
exopie/Data/MRdata_H2.pkl
exopie/Data/MRdata_mantle.pkl
exopie/Data/MRdata_rocky.pkl
exopie/Data/MRdata_water.pkl
exopie-1.2.3.dist-info/LICENSE
exopie-1.2.3.dist-info/METADATA
exopie-1.2.3.dist-info/WHEEL
exopie-1.2.3.dist-info/top_level.txt
exopie-1.2.3.dist-info/RECORD
