Metadata-Version: 2.1
Name: exopie
Version: 1.2.3
Summary: A package for finding exoplanet interiors
Home-page: https://github.com/mplotnyko/exopie/
Author: Mykhaylo Plotnykov
Author-email: mykhaylo.plotnykov@mail.utoronto.ca
Classifier: Programming Language :: Python :: 3
Classifier: License :: OSI Approved :: MIT License
Classifier: Operating System :: OS Independent
Requires-Python: >=3.6
License-File: LICENSE
Requires-Dist: numpy
Requires-Dist: scipy
Provides-Extra: optional
Requires-Dist: corner ; extra == 'optional'
